abstract_solana/__init__.py
abstract_solana/abstract_rpcs/__init__.py
abstract_solana/abstract_rpcs/db_templates.py
abstract_solana/abstract_rpcs/get_api_gui.py
abstract_solana/abstract_rpcs/get_body.py
abstract_solana/abstract_rpcs/getstatics.py
abstract_solana/abstract_rpcs/rate_limiter.py
abstract_solana/abstract_rpcs/solana_rpc_client.py
abstract_solana/abstract_solana_utils/__init__.py
abstract_solana/abstract_solana_utils/bondingCurves.py
abstract_solana/abstract_solana_utils/genesis_functions.py
abstract_solana/abstract_solana_utils/pubKeyUtils.py
abstract_solana/abstract_utils/__init__.py
abstract_solana/abstract_utils/account_key_utils.py
abstract_solana/abstract_utils/constants.py
abstract_solana/abstract_utils/genesis_functions.py
abstract_solana/abstract_utils/index_utils.py
abstract_solana/abstract_utils/keypair_utils.py
abstract_solana/abstract_utils/log_message_functions.py
abstract_solana/abstract_utils/price_utils.py
abstract_solana/abstract_utils/pubKeyUtils.py
abstract_solana/abstract_utils/pubkey_utils.py
abstract_solana/abstract_utils/signature_data_parse.py
abstract_solana/abstract_utils/utils.py
abstract_solana/pumpFun/__init__.py
abstract_solana/pumpFun/constants.py
abstract_solana/pump_functions/__init__.py
abstract_solana/pump_functions/buy_sell_pump.py
abstract_solana/pump_functions/pump_fun_keys.py
abstract_solana/pump_functions/token_utils.py
abstract_solana/rpc_utils/__init__.py
abstract_solana/rpc_utils/rpc_utils.py
abstract_solana/utils/__init__.py
abstract_solana/utils/bondingCurves.py
abstract_solana/utils/genesis_functions.py
abstract_solana/utils/pubKeyUtils.py
abstract_solana-0.0.2.143.dist-info/METADATA
abstract_solana-0.0.2.143.dist-info/WHEEL
abstract_solana-0.0.2.143.dist-info/top_level.txt
abstract_solana-0.0.2.143.dist-info/RECORD
